<?xml version="1.0" encoding="utf-8"?>
<fmg>
<compression>None</compression>
<version>DarkSouls1</version>
<bigendian>False</bigendian>
<entries>
<text id="600">Knight Solaire</text>
<text id="605">Dusk of Oolacile</text>
<text id="631">Shiva</text>
<text id="651">Iron Tarkus</text>
<text id="652">Witch Beatrice</text>
<text id="653">Maneater Mildred</text>
<text id="655">Paladin Leeroy</text>
<text id="656">Knight Kirk</text>
<text id="657">King Jeremiah</text>
<text id="659">Knight Lautrec</text>
<text id="2230">Demon Firesage</text>
<text id="2231">Stray Demon</text>
<text id="2232">Asylum Golem</text>
<text id="2240">Capra Demon</text>
<text id="2250">Taurus Demon</text>
<text id="2320">Iron Golem</text>
<text id="2360">Executioner Smough</text>
<text id="2730">Crossbreed Priscilla</text>
<text id="3230">Moonlight Butterfly</text>
<text id="3320">Pinwheel</text>
<text id="3471">Sanctuary Guardian</text>
<text id="4100">Knight Artorias</text>
<text id="4500">Manus, Father of the Abyss</text>
<text id="4510">Black Dragon Kalameet</text>
<text id="5200">Centipede Demon</text>
<text id="5210">Great Grey Wolf Sif</text>
<text id="5220">Gravelord Nito</text>
<text id="5250">Ceaseless Discharge</text>
<text id="5260">Gaping Dragon</text>
<text id="5270">Dragon Slayer Ornstein</text>
<text id="5280">Chaos Witch Quelaag</text>
<text id="5290">Seath the Scaleless</text>
<text id="5320">Dark Sun Gwyndolin</text>
<text id="5350">Bell Gargoyle</text>
<text id="5370">Gwyn, Lord of Cinder</text>
<text id="5390">Four Kings</text>
<text id="5400">Bed of Chaos</text>
<text id="10000">Gravelord Servant</text>
</entries>
</fmg>